airflow_priority/__init__.py
airflow_priority/common.py
airflow_priority/constants.py
airflow_priority/plugin.py
airflow_priority/tracker.py
airflow_priority/configuration/__init__.py
airflow_priority/configuration/aws.py
airflow_priority/configuration/base.py
airflow_priority/configuration/datadog.py
airflow_priority/configuration/discord.py
airflow_priority/configuration/logfire.py
airflow_priority/configuration/newrelic.py
airflow_priority/configuration/opsgenie.py
airflow_priority/configuration/pagerduty.py
airflow_priority/configuration/priority.py
airflow_priority/configuration/slack.py
airflow_priority/configuration/symphony.py
airflow_priority/models/__init__.py
airflow_priority/plugins/__init__.py
airflow_priority/plugins/aws.py
airflow_priority/plugins/datadog.py
airflow_priority/plugins/discord.py
airflow_priority/plugins/logfire.py
airflow_priority/plugins/newrelic.py
airflow_priority/plugins/opsgenie.py
airflow_priority/plugins/pagerduty.py
airflow_priority/plugins/slack.py
airflow_priority/plugins/symphony.py
airflow_priority/tests/airflow.cfg.base.jinja
airflow_priority/tests/airflow.cfg.jinja
airflow_priority/tests/airflow.cfg2.jinja
airflow_priority/tests/conftest.py
airflow_priority/tests/test_airflow_config.py
airflow_priority/tests/test_common.py
airflow_priority/tests/test_datadog.py
airflow_priority/tests/test_discord.py
airflow_priority/tests/test_logfire.py
airflow_priority/tests/test_newrelic.py
airflow_priority/tests/test_opsgenie.py
airflow_priority/tests/test_pagerduty.py
airflow_priority/tests/test_plugin.py
airflow_priority/tests/test_slack.py
airflow_priority/tests/test_symphony.py
airflow_priority-1.6.1.dist-info/METADATA
airflow_priority-1.6.1.dist-info/WHEEL
airflow_priority-1.6.1.dist-info/entry_points.txt
airflow_priority-1.6.1.dist-info/licenses/LICENSE
airflow_priority-1.6.1.dist-info/RECORD
