Metadata-Version: 2.4
Name: airflow-priority
Version: 1.6.1
Summary: Priority Tags for Airflow Dags
Project-URL: Repository, https://github.com/airflow-laminar/airflow-priority
Project-URL: Homepage, https://github.com/airflow-laminar/airflow-priority
Author-email: the airflow-priority authors <t.paine154@gmail.com>
License: Apache-2.0
License-File: LICENSE
Classifier: Development Status :: 4 - Beta
Classifier: Programming Language :: Python
Classifier: Programming Language :: Python :: 3
Classifier: Programming Language :: Python :: 3.9
Classifier: Programming Language :: Python :: 3.10
Classifier: Programming Language :: Python :: 3.11
Classifier: Programming Language :: Python :: 3.12
Classifier: Programming Language :: Python :: 3.13
Classifier: Programming Language :: Python :: Implementation :: CPython
Classifier: Programming Language :: Python :: Implementation :: PyPy
Requires-Python: >=3.9
Requires-Dist: pydantic>=2
Provides-Extra: aws
Requires-Dist: boto3; extra == 'aws'
Requires-Dist: botocore; extra == 'aws'
Provides-Extra: config
Requires-Dist: airflow-config>=1.9; extra == 'config'
Provides-Extra: datadog
Requires-Dist: datadog-api-client; extra == 'datadog'
Provides-Extra: develop
Requires-Dist: airflow-config>=1.9; extra == 'develop'
Requires-Dist: apache-airflow<3,>=2; extra == 'develop'
Requires-Dist: boto3; extra == 'develop'
Requires-Dist: botocore; extra == 'develop'
Requires-Dist: build; extra == 'develop'
Requires-Dist: bump-my-version; extra == 'develop'
Requires-Dist: check-manifest; extra == 'develop'
Requires-Dist: datadog-api-client; extra == 'develop'
Requires-Dist: discord-py; extra == 'develop'
Requires-Dist: hatchling; extra == 'develop'
Requires-Dist: httpx; extra == 'develop'
Requires-Dist: logfire; extra == 'develop'
Requires-Dist: newrelic-telemetry-sdk; extra == 'develop'
Requires-Dist: opsgenie-sdk; extra == 'develop'
Requires-Dist: pagerduty; extra == 'develop'
Requires-Dist: pytest; extra == 'develop'
Requires-Dist: pytest-cov; extra == 'develop'
Requires-Dist: ruff; extra == 'develop'
Requires-Dist: slack-sdk; extra == 'develop'
Requires-Dist: twine; extra == 'develop'
Requires-Dist: uv; extra == 'develop'
Requires-Dist: wheel; extra == 'develop'
Provides-Extra: discord
Requires-Dist: discord-py; extra == 'discord'
Provides-Extra: logfire
Requires-Dist: logfire; extra == 'logfire'
Provides-Extra: newrelic
Requires-Dist: newrelic-telemetry-sdk; extra == 'newrelic'
Provides-Extra: opsgenie
Requires-Dist: opsgenie-sdk; extra == 'opsgenie'
Provides-Extra: pagerduty
Requires-Dist: pagerduty; extra == 'pagerduty'
Provides-Extra: slack
Requires-Dist: slack-sdk; extra == 'slack'
Provides-Extra: symphony
Requires-Dist: httpx; extra == 'symphony'
